Metadata-Version: 2.1
Name: security_package
Version: 1.7
Summary: A merged package combining gitleaks and zap
Author: Udit Raj Singh
Author-email: uditrajsingh815@example.com
Classifier: Programming Language :: Python :: 3
Classifier: License :: OSI Approved :: MIT License
Classifier: Operating System :: OS Independent
Requires-Python: >=3.6
Requires-Dist: requests >=2.25.1
